sonaris/__init__.py
sonaris/__main__.py
sonaris/api/__init__.py
sonaris/api/dg4202_api.py
sonaris/app.py
sonaris/assets/favicon.ico
sonaris/defaults.py
sonaris/device/__init__.py
sonaris/device/data.py
sonaris/device/device.py
sonaris/device/dg4202.py
sonaris/device/edux1002a.py
sonaris/device/interface.py
sonaris/factory.py
sonaris/frontend/__init__.py
sonaris/frontend/managers/__init__.py
sonaris/frontend/managers/device.py
sonaris/frontend/managers/dg4202.py
sonaris/frontend/managers/edux1002a.py
sonaris/frontend/managers/state_manager.py
sonaris/frontend/pages/__init__.py
sonaris/frontend/pages/general.py
sonaris/frontend/pages/monitor.py
sonaris/frontend/pages/plotter.py
sonaris/frontend/pages/scheduler.py
sonaris/frontend/pages/settings.py
sonaris/frontend/widgets/__init__.py
sonaris/frontend/widgets/gen_oscilloscope.py
sonaris/frontend/widgets/gen_signal.py
sonaris/frontend/widgets/menu.py
sonaris/frontend/widgets/mon_device.py
sonaris/frontend/widgets/sch_exp_popup.py
sonaris/frontend/widgets/sch_experiments.py
sonaris/frontend/widgets/sch_scheduler.py
sonaris/frontend/widgets/sch_task_parameters.py
sonaris/frontend/widgets/sch_task_popup.py
sonaris/frontend/widgets/set_mock.py
sonaris/frontend/widgets/set_state.py
sonaris/frontend/widgets/sidebar.py
sonaris/frontend/widgets/templates.py
sonaris/frontend/widgets/ui_factory.py
sonaris/frontend/widgets/windows.py
sonaris/scheduler/functionmap.py
sonaris/scheduler/models.py
sonaris/scheduler/registry.py
sonaris/scheduler/timekeeper.py
sonaris/scheduler/worker.py
sonaris/services/__init__.py
sonaris/services/container_service.py
sonaris/services/dashboards.py
sonaris/services/datasource.py
sonaris/services/grafana.py
sonaris/services/service.py
sonaris/tasks/__init__.py
sonaris/tasks/config_loader.py
sonaris/tasks/model.py
sonaris/tasks/task_decorator.py
sonaris/tasks/task_validator.py
sonaris/tasks/tasks.py
sonaris/utils/__init__.py
sonaris/utils/container.py
sonaris/utils/log.py
sonaris-0.1.5.dist-info/LICENSE
sonaris-0.1.5.dist-info/METADATA
sonaris-0.1.5.dist-info/WHEEL
sonaris-0.1.5.dist-info/RECORD
